tempyenv/__init__.py
tempyenv/__main__.py
tempyenv/cli.py
tempyenv-1.0.5.dist-info/licenses/LICENSE
tempyenv-1.0.5.dist-info/METADATA
tempyenv-1.0.5.dist-info/WHEEL
tempyenv-1.0.5.dist-info/entry_points.txt
tempyenv-1.0.5.dist-info/top_level.txt
tempyenv-1.0.5.dist-info/RECORD
