Metadata-Version: 2.4
Name: tempyenv
Version: 1.0.5
Summary: An easy and quick way to create a temporary Python virtual environment.
Home-page: https://github.com/outbit/tempyenv
Author: David Whiteside
Author-email: David Whiteside <david@davidwhiteside.com>
License: MIT License
Project-URL: Homepage, https://github.com/outbit/tempyenv
Project-URL: Issues, https://github.com/outbit/tempyenv/issues
Classifier: Programming Language :: Python :: 3
Classifier: License :: OSI Approved :: MIT License
Classifier: Operating System :: OS Independent
Requires-Python: >=3.7
License-File: LICENSE
Dynamic: author
Dynamic: home-page
Dynamic: license-file
Dynamic: requires-python
